[
  {
    "name": "长江电力_5_3",
    "stock_name": "长江电力",
    "entry_window": 5,
    "exit_window": 3,
    "initial_capital": 100000.0,
    "final_value": 90989.82,
    "total_return": -9.01,
    "annual_return": -9.48,
    "buy_hold_return": -9.93,
    "excess_return": 0.92,
    "max_drawdown": -9.36,
    "sharpe_ratio": -2.134,
    "sortino_ratio": -2.038,
    "volatility": 5.41,
    "calmar_ratio": -1.013,
    "win_rate": 22.22,
    "profit_loss_ratio": 0.439,
    "n_trades": 9,
    "avg_holding_days": 9.0,
    "avg_units": 1.0,
    "total_cost": 1230.67,
    "exit_reasons": {
      "exit_signal": 8,
      "final": 1
    },
    "start_date": "2025-07-08",
    "end_date": "2026-07-02",
    "n_trading_days": 239
  },
  {
    "name": "长江电力_5_5",
    "stock_name": "长江电力",
    "entry_window": 5,
    "exit_window": 5,
    "initial_capital": 100000.0,
    "final_value": 90811.4,
    "total_return": -9.19,
    "annual_return": -9.66,
    "buy_hold_return": -9.93,
    "excess_return": 0.74,
    "max_drawdown": -9.54,
    "sharpe_ratio": -1.844,
    "sortino_ratio": -1.878,
    "volatility": 6.34,
    "calmar_ratio": -1.013,
    "win_rate": 25.0,
    "profit_loss_ratio": 0.412,
    "n_trades": 8,
    "avg_holding_days": 12.0,
    "avg_units": 1.0,
    "total_cost": 1084.47,
    "exit_reasons": {
      "stop_loss": 1,
      "exit_signal": 6,
      "final": 1
    },
    "start_date": "2025-07-08",
    "end_date": "2026-07-02",
    "n_trading_days": 239
  },
  {
    "name": "长江电力_10_5",
    "stock_name": "长江电力",
    "entry_window": 10,
    "exit_window": 5,
    "initial_capital": 100000.0,
    "final_value": 96901.23,
    "total_return": -3.1,
    "annual_return": -3.33,
    "buy_hold_return": -11.58,
    "excess_return": 8.48,
    "max_drawdown": -5.73,
    "sharpe_ratio": -1.162,
    "sortino_ratio": -0.918,
    "volatility": 4.56,
    "calmar_ratio": -0.582,
    "win_rate": 50.0,
    "profit_loss_ratio": 0.302,
    "n_trades": 4,
    "avg_holding_days": 15.8,
    "avg_units": 1.0,
    "total_cost": 609.4,
    "exit_reasons": {
      "exit_signal": 3,
      "stop_loss": 1
    },
    "start_date": "2025-07-15",
    "end_date": "2026-07-02",
    "n_trading_days": 234
  },
  {
    "name": "长江电力_10_10",
    "stock_name": "长江电力",
    "entry_window": 10,
    "exit_window": 10,
    "initial_capital": 100000.0,
    "final_value": 92490.11,
    "total_return": -7.51,
    "annual_return": -8.06,
    "buy_hold_return": -11.58,
    "excess_return": 4.07,
    "max_drawdown": -10.02,
    "sharpe_ratio": -1.766,
    "sortino_ratio": -1.738,
    "volatility": 5.82,
    "calmar_ratio": -0.805,
    "win_rate": 0.0,
    "profit_loss_ratio": 0.0,
    "n_trades": 4,
    "avg_holding_days": 24.8,
    "avg_units": 1.0,
    "total_cost": 601.45,
    "exit_reasons": {
      "exit_signal": 3,
      "stop_loss": 1
    },
    "start_date": "2025-07-15",
    "end_date": "2026-07-02",
    "n_trading_days": 234
  },
  {
    "name": "长江电力_15_7",
    "stock_name": "长江电力",
    "entry_window": 15,
    "exit_window": 7,
    "initial_capital": 100000.0,
    "final_value": 97045.35,
    "total_return": -2.95,
    "annual_return": -3.25,
    "buy_hold_return": -8.21,
    "excess_return": 5.25,
    "max_drawdown": -4.67,
    "sharpe_ratio": -1.212,
    "sortino_ratio": -0.772,
    "volatility": 4.31,
    "calmar_ratio": -0.696,
    "win_rate": 33.33,
    "profit_loss_ratio": 0.125,
    "n_trades": 3,
    "avg_holding_days": 16.7,
    "avg_units": 1.0,
    "total_cost": 443.43,
    "exit_reasons": {
      "exit_signal": 3
    },
    "start_date": "2025-07-22",
    "end_date": "2026-07-02",
    "n_trading_days": 229
  },
  {
    "name": "长江电力_20_10",
    "stock_name": "长江电力",
    "entry_window": 20,
    "exit_window": 10,
    "initial_capital": 100000.0,
    "final_value": 93798.17,
    "total_return": -6.2,
    "annual_return": -6.95,
    "buy_hold_return": -5.87,
    "excess_return": -0.33,
    "max_drawdown": -7.41,
    "sharpe_ratio": -1.719,
    "sortino_ratio": -1.499,
    "volatility": 5.29,
    "calmar_ratio": -0.938,
    "win_rate": 0.0,
    "profit_loss_ratio": 0.0,
    "n_trades": 3,
    "avg_holding_days": 27.7,
    "avg_units": 1.0,
    "total_cost": 431.74,
    "exit_reasons": {
      "stop_loss": 1,
      "exit_signal": 2
    },
    "start_date": "2025-07-29",
    "end_date": "2026-07-02",
    "n_trading_days": 224
  },
  {
    "name": "长江电力_30_15",
    "stock_name": "长江电力",
    "entry_window": 30,
    "exit_window": 15,
    "initial_capital": 100000.0,
    "final_value": 95190.84,
    "total_return": -4.81,
    "annual_return": -5.64,
    "buy_hold_return": -2.92,
    "excess_return": -1.89,
    "max_drawdown": -4.81,
    "sharpe_ratio": -2.3,
    "sortino_ratio": -1.087,
    "volatility": 3.38,
    "calmar_ratio": -1.172,
    "win_rate": 0.0,
    "profit_loss_ratio": 0.0,
    "n_trades": 2,
    "avg_holding_days": 14.5,
    "avg_units": 1.0,
    "total_cost": 280.97,
    "exit_reasons": {
      "stop_loss": 2
    },
    "start_date": "2025-08-12",
    "end_date": "2026-07-02",
    "n_trading_days": 214
  },
  {
    "name": "长江电力_55_20",
    "stock_name": "长江电力",
    "entry_window": 55,
    "exit_window": 20,
    "initial_capital": 100000.0,
    "final_value": 95190.84,
    "total_return": -4.81,
    "annual_return": -6.36,
    "buy_hold_return": -2.81,
    "excess_return": -2.0,
    "max_drawdown": -4.81,
    "sharpe_ratio": -2.375,
    "sortino_ratio": -1.195,
    "volatility": 3.6,
    "calmar_ratio": -1.323,
    "win_rate": 0.0,
    "profit_loss_ratio": 0.0,
    "n_trades": 2,
    "avg_holding_days": 14.5,
    "avg_units": 1.0,
    "total_cost": 280.97,
    "exit_reasons": {
      "stop_loss": 2
    },
    "start_date": "2025-09-16",
    "end_date": "2026-07-02",
    "n_trading_days": 189
  },
  {
    "name": "贵州茅台_5_3",
    "stock_name": "贵州茅台",
    "entry_window": 5,
    "exit_window": 3,
    "initial_capital": 100000.0,
    "final_value": 86876.53,
    "total_return": -13.12,
    "annual_return": -13.84,
    "buy_hold_return": -14.92,
    "excess_return": 1.8,
    "max_drawdown": -14.37,
    "sharpe_ratio": -1.971,
    "sortino_ratio": -1.619,
    "volatility": 8.42,
    "calmar_ratio": -0.963,
    "win_rate": 16.67,
    "profit_loss_ratio": 1.242,
    "n_trades": 12,
    "avg_holding_days": 5.2,
    "avg_units": 1.17,
    "total_cost": 1470.06,
    "exit_reasons": {
      "exit_signal": 11,
      "stop_loss": 1
    },
    "start_date": "2025-07-17",
    "end_date": "2026-07-10",
    "n_trading_days": 238
  },
  {
    "name": "贵州茅台_5_5",
    "stock_name": "贵州茅台",
    "entry_window": 5,
    "exit_window": 5,
    "initial_capital": 100000.0,
    "final_value": 84015.51,
    "total_return": -15.98,
    "annual_return": -16.84,
    "buy_hold_return": -14.92,
    "excess_return": -1.06,
    "max_drawdown": -17.19,
    "sharpe_ratio": -2.05,
    "sortino_ratio": -1.893,
    "volatility": 9.77,
    "calmar_ratio": -0.98,
    "win_rate": 18.18,
    "profit_loss_ratio": 0.898,
    "n_trades": 11,
    "avg_holding_days": 8.0,
    "avg_units": 1.18,
    "total_cost": 1354.86,
    "exit_reasons": {
      "stop_loss": 3,
      "exit_signal": 8
    },
    "start_date": "2025-07-17",
    "end_date": "2026-07-10",
    "n_trading_days": 238
  },
  {
    "name": "贵州茅台_10_5",
    "stock_name": "贵州茅台",
    "entry_window": 10,
    "exit_window": 5,
    "initial_capital": 100000.0,
    "final_value": 91407.96,
    "total_return": -8.59,
    "annual_return": -9.26,
    "buy_hold_return": -19.21,
    "excess_return": 10.62,
    "max_drawdown": -8.88,
    "sharpe_ratio": -1.718,
    "sortino_ratio": -1.269,
    "volatility": 6.71,
    "calmar_ratio": -1.042,
    "win_rate": 16.67,
    "profit_loss_ratio": 1.047,
    "n_trades": 6,
    "avg_holding_days": 6.7,
    "avg_units": 1.17,
    "total_cost": 752.87,
    "exit_reasons": {
      "stop_loss": 3,
      "exit_signal": 3
    },
    "start_date": "2025-07-24",
    "end_date": "2026-07-10",
    "n_trading_days": 233
  },
  {
    "name": "贵州茅台_10_10",
    "stock_name": "贵州茅台",
    "entry_window": 10,
    "exit_window": 10,
    "initial_capital": 100000.0,
    "final_value": 88689.05,
    "total_return": -11.31,
    "annual_return": -12.17,
    "buy_hold_return": -19.21,
    "excess_return": 7.9,
    "max_drawdown": -11.31,
    "sharpe_ratio": -2.01,
    "sortino_ratio": -1.618,
    "volatility": 7.34,
    "calmar_ratio": -1.076,
    "win_rate": 16.67,
    "profit_loss_ratio": 0.256,
    "n_trades": 6,
    "avg_holding_days": 7.7,
    "avg_units": 1.17,
    "total_cost": 747.97,
    "exit_reasons": {
      "stop_loss": 4,
      "exit_signal": 2
    },
    "start_date": "2025-07-24",
    "end_date": "2026-07-10",
    "n_trading_days": 233
  },
  {
    "name": "贵州茅台_15_7",
    "stock_name": "贵州茅台",
    "entry_window": 15,
    "exit_window": 7,
    "initial_capital": 100000.0,
    "final_value": 94283.94,
    "total_return": -5.72,
    "annual_return": -6.3,
    "buy_hold_return": -15.24,
    "excess_return": 9.53,
    "max_drawdown": -6.67,
    "sharpe_ratio": -1.579,
    "sortino_ratio": -0.858,
    "volatility": 5.32,
    "calmar_ratio": -0.945,
    "win_rate": 33.33,
    "profit_loss_ratio": 0.459,
    "n_trades": 3,
    "avg_holding_days": 6.7,
    "avg_units": 1.33,
    "total_cost": 412.33,
    "exit_reasons": {
      "stop_loss": 2,
      "exit_signal": 1
    },
    "start_date": "2025-07-31",
    "end_date": "2026-07-10",
    "n_trading_days": 228
  },
  {
    "name": "贵州茅台_20_10",
    "stock_name": "贵州茅台",
    "entry_window": 20,
    "exit_window": 10,
    "initial_capital": 100000.0,
    "final_value": 94527.03,
    "total_return": -5.47,
    "annual_return": -6.16,
    "buy_hold_return": -15.28,
    "excess_return": 9.81,
    "max_drawdown": -6.94,
    "sharpe_ratio": -1.416,
    "sortino_ratio": -0.86,
    "volatility": 5.81,
    "calmar_ratio": -0.888,
    "win_rate": 33.33,
    "profit_loss_ratio": 0.23,
    "n_trades": 3,
    "avg_holding_days": 7.7,
    "avg_units": 1.33,
    "total_cost": 424.13,
    "exit_reasons": {
      "stop_loss": 2,
      "exit_signal": 1
    },
    "start_date": "2025-08-07",
    "end_date": "2026-07-10",
    "n_trading_days": 223
  },
  {
    "name": "贵州茅台_30_15",
    "stock_name": "贵州茅台",
    "entry_window": 30,
    "exit_window": 15,
    "initial_capital": 100000.0,
    "final_value": 93542.01,
    "total_return": -6.46,
    "annual_return": -7.59,
    "buy_hold_return": -16.8,
    "excess_return": 10.34,
    "max_drawdown": -6.55,
    "sharpe_ratio": -2.033,
    "sortino_ratio": -1.115,
    "volatility": 4.83,
    "calmar_ratio": -1.16,
    "win_rate": 0.0,
    "profit_loss_ratio": 0.0,
    "n_trades": 2,
    "avg_holding_days": 9.5,
    "avg_units": 1.5,
    "total_cost": 276.6,
    "exit_reasons": {
      "stop_loss": 2
    },
    "start_date": "2025-08-21",
    "end_date": "2026-07-10",
    "n_trading_days": 213
  },
  {
    "name": "贵州茅台_55_20",
    "stock_name": "贵州茅台",
    "entry_window": 55,
    "exit_window": 20,
    "initial_capital": 100000.0,
    "final_value": 96119.43,
    "total_return": -3.88,
    "annual_return": -5.17,
    "buy_hold_return": -16.26,
    "excess_return": 12.38,
    "max_drawdown": -4.71,
    "sharpe_ratio": -1.859,
    "sortino_ratio": -0.443,
    "volatility": 3.9,
    "calmar_ratio": -1.096,
    "win_rate": 0.0,
    "profit_loss_ratio": 0.0,
    "n_trades": 1,
    "avg_holding_days": 6.0,
    "avg_units": 2.0,
    "total_cost": 171.09,
    "exit_reasons": {
      "stop_loss": 1
    },
    "start_date": "2025-09-25",
    "end_date": "2026-07-10",
    "n_trading_days": 188
  },
  {
    "name": "中国平安_5_3",
    "stock_name": "中国平安",
    "entry_window": 5,
    "exit_window": 3,
    "initial_capital": 100000.0,
    "final_value": 95785.43,
    "total_return": -4.21,
    "annual_return": -4.46,
    "buy_hold_return": -12.9,
    "excess_return": 8.69,
    "max_drawdown": -10.53,
    "sharpe_ratio": -0.616,
    "sortino_ratio": -0.691,
    "volatility": 9.89,
    "calmar_ratio": -0.423,
    "win_rate": 18.18,
    "profit_loss_ratio": 2.673,
    "n_trades": 11,
    "avg_holding_days": 7.8,
    "avg_units": 1.27,
    "total_cost": 1179.1,
    "exit_reasons": {
      "exit_signal": 10,
      "stop_loss": 1
    },
    "start_date": "2025-07-17",
    "end_date": "2026-07-10",
    "n_trading_days": 238
  },
  {
    "name": "中国平安_5_5",
    "stock_name": "中国平安",
    "entry_window": 5,
    "exit_window": 5,
    "initial_capital": 100000.0,
    "final_value": 100692.43,
    "total_return": 0.69,
    "annual_return": 0.73,
    "buy_hold_return": -12.9,
    "excess_return": 13.6,
    "max_drawdown": -11.12,
    "sharpe_ratio": -0.036,
    "sortino_ratio": -0.044,
    "volatility": 12.81,
    "calmar_ratio": 0.066,
    "win_rate": 28.57,
    "profit_loss_ratio": 2.099,
    "n_trades": 7,
    "avg_holding_days": 17.1,
    "avg_units": 1.29,
    "total_cost": 769.8,
    "exit_reasons": {
      "exit_signal": 5,
      "stop_loss": 2
    },
    "start_date": "2025-07-17",
    "end_date": "2026-07-10",
    "n_trading_days": 238
  },
  {
    "name": "中国平安_10_5",
    "stock_name": "中国平安",
    "entry_window": 10,
    "exit_window": 5,
    "initial_capital": 100000.0,
    "final_value": 97907.27,
    "total_return": -2.09,
    "annual_return": -2.26,
    "buy_hold_return": -15.62,
    "excess_return": 13.53,
    "max_drawdown": -12.0,
    "sharpe_ratio": -0.323,
    "sortino_ratio": -0.339,
    "volatility": 11.35,
    "calmar_ratio": -0.188,
    "win_rate": 33.33,
    "profit_loss_ratio": 1.257,
    "n_trades": 6,
    "avg_holding_days": 16.3,
    "avg_units": 1.17,
    "total_cost": 572.56,
    "exit_reasons": {
      "exit_signal": 5,
      "stop_loss": 1
    },
    "start_date": "2025-07-24",
    "end_date": "2026-07-10",
    "n_trading_days": 233
  },
  {
    "name": "中国平安_10_10",
    "stock_name": "中国平安",
    "entry_window": 10,
    "exit_window": 10,
    "initial_capital": 100000.0,
    "final_value": 97855.97,
    "total_return": -2.14,
    "annual_return": -2.32,
    "buy_hold_return": -15.62,
    "excess_return": 13.48,
    "max_drawdown": -12.43,
    "sharpe_ratio": -0.321,
    "sortino_ratio": -0.347,
    "volatility": 11.52,
    "calmar_ratio": -0.186,
    "win_rate": 40.0,
    "profit_loss_ratio": 0.972,
    "n_trades": 5,
    "avg_holding_days": 21.2,
    "avg_units": 1.4,
    "total_cost": 571.51,
    "exit_reasons": {
      "stop_loss": 1,
      "exit_signal": 4
    },
    "start_date": "2025-07-24",
    "end_date": "2026-07-10",
    "n_trading_days": 233
  },
  {
    "name": "中国平安_15_7",
    "stock_name": "中国平安",
    "entry_window": 15,
    "exit_window": 7,
    "initial_capital": 100000.0,
    "final_value": 99803.91,
    "total_return": -0.2,
    "annual_return": -0.22,
    "buy_hold_return": -15.69,
    "excess_return": 15.5,
    "max_drawdown": -10.96,
    "sharpe_ratio": -0.15,
    "sortino_ratio": -0.124,
    "volatility": 10.87,
    "calmar_ratio": -0.02,
    "win_rate": 50.0,
    "profit_loss_ratio": 0.808,
    "n_trades": 4,
    "avg_holding_days": 14.0,
    "avg_units": 1.25,
    "total_cost": 427.68,
    "exit_reasons": {
      "stop_loss": 1,
      "exit_signal": 3
    },
    "start_date": "2025-07-31",
    "end_date": "2026-07-10",
    "n_trading_days": 228
  },
  {
    "name": "中国平安_20_10",
    "stock_name": "中国平安",
    "entry_window": 20,
    "exit_window": 10,
    "initial_capital": 100000.0,
    "final_value": 102430.55,
    "total_return": 2.43,
    "annual_return": 2.75,
    "buy_hold_return": -15.96,
    "excess_return": 18.4,
    "max_drawdown": -9.23,
    "sharpe_ratio": 0.121,
    "sortino_ratio": 0.087,
    "volatility": 10.54,
    "calmar_ratio": 0.298,
    "win_rate": 50.0,
    "profit_loss_ratio": 4.692,
    "n_trades": 2,
    "avg_holding_days": 20.5,
    "avg_units": 1.5,
    "total_cost": 275.2,
    "exit_reasons": {
      "exit_signal": 2
    },
    "start_date": "2025-08-07",
    "end_date": "2026-07-10",
    "n_trading_days": 223
  },
  {
    "name": "中国平安_30_15",
    "stock_name": "中国平安",
    "entry_window": 30,
    "exit_window": 15,
    "initial_capital": 100000.0,
    "final_value": 98099.87,
    "total_return": -1.9,
    "annual_return": -2.24,
    "buy_hold_return": -17.01,
    "excess_return": 15.11,
    "max_drawdown": -9.23,
    "sharpe_ratio": -0.369,
    "sortino_ratio": -0.237,
    "volatility": 10.21,
    "calmar_ratio": -0.243,
    "win_rate": 50.0,
    "profit_loss_ratio": 1.384,
    "n_trades": 2,
    "avg_holding_days": 15.0,
    "avg_units": 1.5,
    "total_cost": 274.04,
    "exit_reasons": {
      "stop_loss": 2
    },
    "start_date": "2025-08-21",
    "end_date": "2026-07-10",
    "n_trading_days": 213
  },
  {
    "name": "中国平安_55_20",
    "stock_name": "中国平安",
    "entry_window": 55,
    "exit_window": 20,
    "initial_capital": 100000.0,
    "final_value": 101272.05,
    "total_return": 1.27,
    "annual_return": 1.71,
    "buy_hold_return": -10.18,
    "excess_return": 11.46,
    "max_drawdown": -10.99,
    "sharpe_ratio": 0.033,
    "sortino_ratio": 0.023,
    "volatility": 11.73,
    "calmar_ratio": 0.155,
    "win_rate": 100.0,
    "profit_loss_ratio": 0.0,
    "n_trades": 1,
    "avg_holding_days": 27.0,
    "avg_units": 2.0,
    "total_cost": 182.49,
    "exit_reasons": {
      "exit_signal": 1
    },
    "start_date": "2025-09-25",
    "end_date": "2026-07-10",
    "n_trading_days": 188
  }
]